scalenet/__init__.py
scalenet/add.py
scalenet/identity.py
scalenet/initialization.py
scalenet/model.py
scalenet/residuals.py
scalenet/scalenet.py
scalenet/scalenet_base.py
scalenet/scalenet_new.py
scalenet/sequence.py
scalenet/tools.py
scalenet/upsample_residuals.py
scalenet-0.1.0.dist-info/LICENSE
scalenet-0.1.0.dist-info/METADATA
scalenet-0.1.0.dist-info/WHEEL
scalenet-0.1.0.dist-info/top_level.txt
scalenet-0.1.0.dist-info/RECORD
