Metadata-Version: 2.1
Name: scalenet
Version: 0.1.0
Summary: A universal pytorch module for implementing multiscale architectures (UNet, spatial pyramid, SpyNet, res-Unet)
Home-page: https://github.com/supersergiy/scalenet
Author: Sergiy Popovych
Author-email: sergiy.popovich@gmail.com
License: UNKNOWN
Platform: UNKNOWN
Requires-Dist: torch
Requires-Dist: numpy
Requires-Dist: six
